transmat/__init__.py
transmat/transmat.py
transmat-0.1.dist-info/LICENSE
transmat-0.1.dist-info/METADATA
transmat-0.1.dist-info/WHEEL
transmat-0.1.dist-info/entry_points.txt
transmat-0.1.dist-info/top_level.txt
transmat-0.1.dist-info/RECORD
