Metadata-Version: 2.1
Name: transmat
Version: 0.1
Summary: Upload and download file via WeTransfer from terminal
Home-page: https://github.com/sirowain/transmat
Author: Riccardo Albertini
Author-email: ssirowain@gmail.com
License: UNKNOWN
Platform: UNKNOWN
Classifier: Programming Language :: Python :: 3
Classifier: License :: OSI Approved :: MIT License
Classifier: Operating System :: OS Independent
Requires-Dist: requests
Requires-Dist: py3wetransfer
